{
  "chelek": "YD",
  "siman": 237,
  "chelekTitle": "Yoreh Deah",
  "seifCount": 12,
  "fetchedAt": "2026-07-08T00:01:26.033Z",
  "sa": [
    {
      "seif": 1,
      "he": "הנשבע אם צריך לישבע בשם או בכינוי. ובו י\"ב סעיפים:האומר אני נשבע שאעשה דבר פלוני או שלא אעשנו הרי זה שבועה אע\"פ שלא הזכיר לא שם ולא כינוי: הגה ואין חלוק אם הוציא השבועה בלשון הקודש או בכל לשון שיאמרנה (תשובת הרשב\"א סימן תתמ\"ב ובמרדכי פ' שבועות שתים וברמב\"ם פי\"ב מהלכות שבועות):",
      "en": "",
      "ref": "Shulchan Arukh, Yoreh Deah 237:1"
    },
    {
      "seif": 2,
      "he": "השביעו אחר שאמר לו אני משביעך שתעשה דבר פלוני או שלא תעשנו וענה אמן או דבר שנשמע ממנו שמקבל שבועתו כגון שאמר הן או קבלתי דבריך הוי כאלו נשבע בעצמו ואפילו השביעו עובד כוכבים או קטן:",
      "en": "",
      "ref": "Shulchan Arukh, Yoreh Deah 237:2"
    },
    {
      "seif": 3,
      "he": "אמר אהא באלה או בארור אם לא אעשה דבר פלוני או שאמר ליה אחר כן וקבל דבריו הוי כשבועה אף על פי שלא הזכיר לא שם ולא כינוי:",
      "en": "",
      "ref": "Shulchan Arukh, Yoreh Deah 237:3"
    },
    {
      "seif": 4,
      "he": "האומר מבטא שאעשה דבר פלוני או שלא אעשנו הוי כאילו אומר שבועה:",
      "en": "",
      "ref": "Shulchan Arukh, Yoreh Deah 237:4"
    },
    {
      "seif": 5,
      "he": "האומר פעמים על דבר אחד אעשנו או לא אעשנו הוי שבועה והוא שיתכוין לשם שבועה במה דברים אמורים כשאמרם זה אחר זה בלא הפסק אבל אם מבקשים אותו עליו והוא אמר לא אעשנו ובקשוהו עוד ואמר לא אעשנו לא הוי שבועה:",
      "en": "",
      "ref": "Shulchan Arukh, Yoreh Deah 237:5"
    },
    {
      "seif": 6,
      "he": "מי שנשבע בשמים ובארץ ושמש וכיוצא בהם אע\"פ שאין כונתו אלא למי שבראם אינה שבועה וה\"ה לנשבע בנביא מהנביאים (או בשאר כתב מכתבי הקודש) (הרמב\"ם) או בשלחן המקדש או באחד מכלי הקדש ואף ע\"פ כן מאיימין עליהן ומראין להם שזו שבועה כדי שלא ינהגו קלות ראש בשבועות ומתירים להם: הגה וכל זה שלא נטל בידו אבל אם נטל בידו כתב אשורית אפילו אינו רק חכמה חיצונית או אל\"ף בי\"ת שאין בו רק אותיות אם נשבע בהן והן בידו הוי שבועה (סברת הב\"י) וע\"ל סי' רי\"ב וה\"ה אם לא אחזן בידו והיו מונחים לפניו ואמר במה שכתוב בהן:",
      "en": "",
      "ref": "Shulchan Arukh, Yoreh Deah 237:6"
    },
    {
      "seif": 7,
      "he": "הנשבע בעשרת הדברות שבועה גמורה היא (ועיין לעיל סימן רי\"ב):",
      "en": "",
      "ref": "Shulchan Arukh, Yoreh Deah 237:7"
    },
    {
      "seif": 8,
      "he": "ימין שבועה וכן שמאל דכתיב נשבע יי' בימינו ובזרוע עזו (והוא שיכוין ג\"כ לימין ושמאל שאמר הקב\"ה) (טור בשם הראב\"ד):",
      "en": "",
      "ref": "Shulchan Arukh, Yoreh Deah 237:8"
    },
    {
      "seif": 9,
      "he": "ידות שבועה כשבועה כיצד ידות אמר כנדר רשעים שלא אוכל ככר זה:",
      "en": "",
      "ref": "Shulchan Arukh, Yoreh Deah 237:9"
    },
    {
      "seif": 10,
      "he": "כינוי שבועה כשבועה כיצד שבותה או שבוקה שלא אוכל ככר זה או מומי אומי אבל אמר באומתא או באומי בבי\"ת אינו כלום ואלו הכנויים הם כפי זמנם לבני אדם שלא היו בקיאים בטיב לשון הקדש והכל לפי הזמן והמקום להוסיף בכינויים אלו או לגרוע מהם (ד\"ע בב\"י) : הגה אותן שרגילין לומר בלשון הקודש אמונה אעשה או לא אעשה אף על פי שהן כנדרי זרוזין מ\"מ בעי התרה. (הגהות מיימוני פ\"ד דנדרים בשם מהר\"מ):",
      "en": "",
      "ref": "Shulchan Arukh, Yoreh Deah 237:10"
    },
    {
      "seif": 11,
      "he": "אמר לחבירו שבועה שאיני אוכל לך או השבועה לא אוכל לך או לשבועה לא אוכל לך אסור לאכול עמו:",
      "en": "",
      "ref": "Shulchan Arukh, Yoreh Deah 237:11"
    },
    {
      "seif": 12,
      "he": "אמר השבועה שאוכל לך נשבע שיאכל עמו ואין חילוק בין הפציר בו תחלה שיאכל עמו או לא הפציר ויש מי שאומר שאם הפציר בו תחלה שיאכל עמו ואמר שבועה שאוכל לך אסור לאכול עמו:",
      "en": "",
      "ref": "Shulchan Arukh, Yoreh Deah 237:12"
    }
  ],
  "commentaries": {
    "bg": {
      "id": "bg",
      "name": "Be'er HaGolah",
      "hebrew": "באר הגולה",
      "seifim": {
        "1": {
          "he": "טור בשם הרמב\"ם בפ\"ב מה' שבועות ובשם הרא\"ש אביו דלא גרע מידות שבועה שהם כשבועות וכתב הרמב\"ם שם דלא מתחייב קרבן עד שיזכיר שם מן השמות המיוחדים או כינוי מן הכינוין:",
          "en": "",
          "ref": "Be'er HaGolah on Shulchan Arukh, Yoreh De'ah 237:1"
        },
        "2": {
          "he": "שם מדברי הרמב\"ם שם ממימרא דשמואל שבועות דף כ\"ט ע\"ב:",
          "en": "",
          "ref": "Be'er HaGolah on Shulchan Arukh, Yoreh De'ah 237:2"
        },
        "3": {
          "he": "ברייתא שם דף ל\"ה ודף ל\"ו ממימרא דרבי אבהו:",
          "en": "",
          "ref": "Be'er HaGolah on Shulchan Arukh, Yoreh De'ah 237:3"
        },
        "4": {
          "he": "מהא דשמואל הנזכר לעיל:",
          "en": "",
          "ref": "Be'er HaGolah on Shulchan Arukh, Yoreh De'ah 237:4"
        },
        "5": {
          "he": "ברייתא שם דף כ' ע\"א:",
          "en": "",
          "ref": "Be'er HaGolah on Shulchan Arukh, Yoreh De'ah 237:5"
        },
        "6": {
          "he": "מימרא דר\"א וכדמפרש רבא שם בשבועו' דף ל\"ו ע\"א:",
          "en": "",
          "ref": "Be'er HaGolah on Shulchan Arukh, Yoreh De'ah 237:6"
        },
        "7": {
          "he": "הרא\"ש שם וכ\"כ הר\"ן שם בשם הראב\"ד והביאו הטור:",
          "en": "",
          "ref": "Be'er HaGolah on Shulchan Arukh, Yoreh De'ah 237:7"
        },
        "8": {
          "he": "ג\"ז מדברי הרא\"ש שם ויליף לה מתרי לאוי דאמר הקב\"ה לנח דהוי זה אחר זה בלא הפסק:",
          "en": "",
          "ref": "Be'er HaGolah on Shulchan Arukh, Yoreh De'ah 237:8"
        },
        "9": {
          "he": "לשון הרמב\"ם בפי\"ב מה\"ש דין ג' ממשנ' שם דף ל\"ה ע\"א:",
          "en": "",
          "ref": "Be'er HaGolah on Shulchan Arukh, Yoreh De'ah 237:9"
        },
        "10": {
          "he": "הגהת מרדכי דשבועות שם תשובת הר\"מ:",
          "en": "",
          "ref": "Be'er HaGolah on Shulchan Arukh, Yoreh De'ah 237:10"
        },
        "11": {
          "he": "הרא\"ש והמרדכי שכתבו בשם רב האי ולזה הסכים הב\"י:",
          "en": "",
          "ref": "Be'er HaGolah on Shulchan Arukh, Yoreh De'ah 237:11"
        },
        "12": {
          "he": "תשובת מהר\"מ הביאו המרדכי פ\"ג דשבועות:",
          "en": "",
          "ref": "Be'er HaGolah on Shulchan Arukh, Yoreh De'ah 237:12"
        },
        "13": {
          "he": "טור בשם הרמב\"ם בפ\"ב מה\"ש מברייתא דנזיר דף ג' ע\"ב:",
          "en": "",
          "ref": "Be'er HaGolah on Shulchan Arukh, Yoreh De'ah 237:13"
        },
        "14": {
          "he": "משנה ריש נדרים:",
          "en": "",
          "ref": "Be'er HaGolah on Shulchan Arukh, Yoreh De'ah 237:14"
        },
        "15": {
          "he": "משנה דף ח' ע\"א משום דרשעים רגילים לישבע הוי כמוציא שבועה מפיו:",
          "en": "",
          "ref": "Be'er HaGolah on Shulchan Arukh, Yoreh De'ah 237:15"
        },
        "16": {
          "he": "שם במשנה:",
          "en": "",
          "ref": "Be'er HaGolah on Shulchan Arukh, Yoreh De'ah 237:16"
        },
        "17": {
          "he": "משנה שם דף י' ע\"א:",
          "en": "",
          "ref": "Be'er HaGolah on Shulchan Arukh, Yoreh De'ah 237:17"
        },
        "18": {
          "he": "שם במשנה וברייתא שם ע\"ב כגירסת הרא\"ש והר\"ן שם:",
          "en": "",
          "ref": "Be'er HaGolah on Shulchan Arukh, Yoreh De'ah 237:18"
        },
        "19": {
          "he": "מדברי הרמב\"ם פ\"ב מה\"ש ופ\"א מה\"נ ופ\"א מהלכות נזיר וכרבי יוחנן שם דף י' ע\"א דאמר לשון העמים הם כלומר שאינם בקיאים בלשון הקדש:",
          "en": "",
          "ref": "Be'er HaGolah on Shulchan Arukh, Yoreh De'ah 237:19"
        },
        "20": {
          "he": "משנה שם דף ט\"ו ע\"א:",
          "en": "",
          "ref": "Be'er HaGolah on Shulchan Arukh, Yoreh De'ah 237:20"
        },
        "21": {
          "he": "פשוט שם בגמרא:",
          "en": "",
          "ref": "Be'er HaGolah on Shulchan Arukh, Yoreh De'ah 237:21"
        },
        "22": {
          "he": "שם במשנה והלמ\"ד בפתח דהוי כמו לא שבועה לא אוכל ויש דגרסי הכי במשנה דאיכא למישמע מיניה הא מה שאוכל לך יהא אסור בשבועה:",
          "en": "",
          "ref": "Be'er HaGolah on Shulchan Arukh, Yoreh De'ah 237:22"
        },
        "23": {
          "he": "משנה שבועות דף י\"ט ע\"ב",
          "en": "",
          "ref": "Be'er HaGolah on Shulchan Arukh, Yoreh De'ah 237:23"
        },
        "24": {
          "he": "כאוקימתא דרב אשי שם דף כ' ע\"א ובנדרים שם הרמב\"ן והרא\"ש שם:",
          "en": "",
          "ref": "Be'er HaGolah on Shulchan Arukh, Yoreh De'ah 237:24"
        },
        "25": {
          "he": "הרמב\"ם בפ\"ד מה\"ש וכ\"כ הר\"ן וכאביי משום דלאוקימתא דרב אשי צריכין לשבש מתני':",
          "en": "",
          "ref": "Be'er HaGolah on Shulchan Arukh, Yoreh De'ah 237:25"
        }
      }
    },
    "shach": {
      "id": "shach",
      "name": "Shach",
      "hebrew": "שך",
      "seifim": {
        "1": {
          "he": "ה\"ז שבועה. להיש פוסקים איסורא איכא וליש פוסקים מלקות נמי איכא דלא גרע מידות שבועה:",
          "en": "",
          "ref": "Siftei Kohen on Shulchan Arukh, Yoreh De'ah 237:1"
        },
        "2": {
          "he": "או בכל לשון כו'. כתוב בתשובת מהר\"מ דפוס פראג סי' ו' בשם ריב\"א דאם הזכיר השם בל' לעז כגון דיא\"ו (או גאט) אפילו לא הזכיר בתחלת דבריו לשם שבועה מועיל מטעם יד וע\"ש בארוכה:",
          "en": "",
          "ref": "Siftei Kohen on Shulchan Arukh, Yoreh De'ah 237:2"
        },
        "3": {
          "he": "וענה אמן כו'. ע\"ל סימן ר\"ט:",
          "en": "",
          "ref": "Siftei Kohen on Shulchan Arukh, Yoreh De'ah 237:3"
        },
        "4": {
          "he": "אם לא אעשה דבר פלוני. או אם אעשה דבר פלוני:",
          "en": "",
          "ref": "Siftei Kohen on Shulchan Arukh, Yoreh De'ah 237:4"
        },
        "5": {
          "he": "מבטא כו'. דכתיב כי יבטא בשפתים:",
          "en": "",
          "ref": "Siftei Kohen on Shulchan Arukh, Yoreh De'ah 237:5"
        },
        "6": {
          "he": "האומר פעמים כו'. דכתיב ולא יכרת כל בשר עוד ממי המבול וגו' ולא יהיה עוד המים למבול וגו' וכתיב כי מי נח זאת לי אשר נשבעתי מדלאו לאו שבוע' הן הן נמי שבועה:",
          "en": "",
          "ref": "Siftei Kohen on Shulchan Arukh, Yoreh De'ah 237:6"
        },
        "7": {
          "he": "והוא שיתכוון כו'. משמע ואע\"פ שלא הזכיר שבועה קודם לכן ותמיהני על מ\"ש הר\"ף בהגהת תשב\"ץ סימן ת\"א דהיינו דוקא שהזכיר שבועה קודם שאמר לאו לאו או הן הן כו' דא\"כ אפילו אמר פעם אחת לאו או הן הוי שבועה דלא גרע מידות ואפשר מיירי שהזכיר מקודם לזה שבועה ואח\"כ הפסיק בנתיים בענין דלא הוי יד:",
          "en": "",
          "ref": "Siftei Kohen on Shulchan Arukh, Yoreh De'ah 237:7"
        },
        "8": {
          "he": "וה\"ה לנשבע בנביא כו'. אף על פי שאין כוונתו אלא למי ששלח נביא זה או למי שצוה בכתב זה:",
          "en": "",
          "ref": "Siftei Kohen on Shulchan Arukh, Yoreh De'ah 237:8"
        },
        "9": {
          "he": "או בשאר כתב מכתבי הקודש. אבל הנשבע בתורה בכל ענין צריך התרה כדכתב הרב לעיל סי' רי\"ב:",
          "en": "",
          "ref": "Siftei Kohen on Shulchan Arukh, Yoreh De'ah 237:9"
        },
        "10": {
          "he": "או בשלחן כו'. ע\"ל סימן ר\"ד ס\"ב בהג\"ה:",
          "en": "",
          "ref": "Siftei Kohen on Shulchan Arukh, Yoreh De'ah 237:10"
        },
        "11": {
          "he": "אבל אם נטל בידו כו'. וכתוב בתשובת מהר\"מ מינץ סימן ע\"ו דאם הניח ידו עליהן דינו כנטלם בידו דא\"צ הגבהה אלא אחיזה בעלמא וע\"ש שהאריך:",
          "en": "",
          "ref": "Siftei Kohen on Shulchan Arukh, Yoreh De'ah 237:11"
        },
        "12": {
          "he": "ואמר במה שכתוב בהן. כתוב בתשובת מהר\"מ מינ\"ץ שם דאם פתחן ונשבע בהן הוי כאומר במה שכתוב בהן ואע\"ג דמיירי שם בעשרת הדברות נראה דה\"ה לכל ספרי הקדש דחד טעמא אית להו:",
          "en": "",
          "ref": "Siftei Kohen on Shulchan Arukh, Yoreh De'ah 237:12"
        },
        "13": {
          "he": "הנשבע בעשרת הדברות כו'. משמע דאם אמר רק אני נשבע בי' דברות אע\"פ שאינו אוחזן בידו שבועה גמורה היא ובתשובת מהר\"מ מינ\"ץ סימן מ\"ו כתב דבעינן אוחזן בידו מיהו נראה דהיינו מדינא דגם בנשבע בתורה בעינן נקיט ליה בידים מדינא אבל לפי מ\"ש הב\"י והרב לעיל סימן רי\"ב דבנשבע בתורה בכל ענין צריך התרה כיון שיש גאונים מחמירים דאפילו התרה אינו מועיל א\"כ גם בי' דברות מחמירים התם הנך גאונים א\"כ בכל ענין צריך התרה וכן משמע בתשובת מהר\"מ מינ\"ץ שם ע\"ש:",
          "en": "",
          "ref": "Siftei Kohen on Shulchan Arukh, Yoreh De'ah 237:13"
        },
        "14": {
          "he": "והוא שיכוין כו'. כלומר שכוונתו לישבע בימין ושמאל של הקב\"ה וכן משמע בל' הראב\"ד שבטור וז\"ל אם נתכוין לימין ושמאל הבורא הוי שבועה עד כאן וכ\"כ העט\"ז והוא שיכוין לימין ושמאל שאמר הקב\"ה דהיינו ימינו ושמאלו יתברך ע\"כ וכן משמע בפרישה אבל הב\"ח נראה שלא הבין כן לכן כתב תימה כי נתכוין לימין שאמר הבורא מאי הוי כיון דאיכא מידי אחרינא דמקרי ימין ושמאל ומ\"ש מהנשבע בשמים ובארץ ועוד דלא עדיף משאמר בפירוש שבועה דלדעת הרמב\"ם צריך שיזכור שם או כינוי בפירוש לענין קרבן הלכך נ\"ל עיקר דאף בימין ושמחל צריך שיזכור השם והכינוי ואעפ\"כ צריך לכוין לימין ושמאל שאמר הקב\"ה דאל\"כ לא הוי שבועה לענין קרבן ולמלקות וכדין לאו לאו עכ\"ל גם מ\"ש דאף בימין ושמאל צריך שיזכיר השם והכנוי ואעפ\"כ צריך שיכוין לימין ושמאל כו' לא עמדתי על סוף דעתו דכיון דמזכיר השם והכינוי למה לימין ושמאל אין לך שבועה גדולה מזה אלא ודאי שאין מזכיר לא שם ולא כינוי ואפ\"ה הוי שבועה ול\"ד לנשבע בשמים ובארץ דשמים וארץ לאו כינויים הן אבל ימין ושמאל כינויים הן והוי כאילו נשבע בהקב\"ה עצמו שהרי הקב\"ה נשבע בימינו ובזרוע עוזו והלכך כשנתכוין לימין ושמאל הבורא הוי שבועה גמורה:",
          "en": "",
          "ref": "Siftei Kohen on Shulchan Arukh, Yoreh De'ah 237:14"
        },
        "15": {
          "he": "כנדר רשעים כו'. דכיון דרשעים רגילין לישבע הוי כמוציא שבועה מפיו וע\"ל סימן ר\"ו ס\"ד:",
          "en": "",
          "ref": "Siftei Kohen on Shulchan Arukh, Yoreh De'ah 237:15"
        },
        "16": {
          "he": "כינוי כו'. ע\"ל סימן ר\"ז:",
          "en": "",
          "ref": "Siftei Kohen on Shulchan Arukh, Yoreh De'ah 237:16"
        },
        "17": {
          "he": "אותן שרגילים לומר בין ליהודים בין לעובדי כוכבים בלשון אמונה שלא אעשה כו'. כן הוא בהגהת מיי' שם ואינו שם מלשון הקדש וכן הוא בד\"מ ר\"ס רל\"ב.",
          "en": "",
          "ref": "Siftei Kohen on Shulchan Arukh, Yoreh De'ah 237:17"
        }
      }
    },
    "taz": {
      "id": "taz",
      "name": "Taz",
      "hebrew": "ט\"ז",
      "seifim": {
        "1": {
          "he": "עובד כוכבים או קטן. וראיה מנבוכדנצר שהשביע לצדקיה ויתרו למשה וקטן לא גרע מעובד כוכבים:",
          "en": "",
          "ref": "Turei Zahav on Shulchan Arukh, Yoreh De'ah 237:1"
        },
        "2": {
          "he": "האומר מבטא. הוא לשון הפסוק יבטא בשפתים:",
          "en": "",
          "ref": "Turei Zahav on Shulchan Arukh, Yoreh De'ah 237:2"
        },
        "3": {
          "he": "הוי שבועה. נלמד ממה דכתיב אשר נשבעתי על מי נח ולא מצינו שעשה שבועה רק מה שאמר שני פעמים לא אוסיף ומדלאו לאו הוה שבועה הן הן נמי שבועה:",
          "en": "",
          "ref": "Turei Zahav on Shulchan Arukh, Yoreh De'ah 237:3"
        },
        "4": {
          "he": "לשם שבועה. פי' כשם שהקב\"ה כפל לשם שבועה וזהו שכתב הראב\"ד להן הן שאמר הבורא שתמה הטור עליו:",
          "en": "",
          "ref": "Turei Zahav on Shulchan Arukh, Yoreh De'ah 237:4"
        },
        "5": {
          "he": "או בשלחן המקדש. עיין מה שכתבתי בסימן ר\"ד סעיף ב' מה שיש לתמוה על רמ\"א שם מכאן: ומ\"ש כנדרי רשעים כיון דרשעים רגילים לישבע הוה כמוציא שבועה מפיו במה שקבל עליו כנדר רשעים: ומ\"ש שאיני אוכל לך כן הנוסחא גם במקצת טורים אבל הוא טעות סופר דאם כן פשיטא וצ\"ל שאי אוכל לך דהכי אמרינן בגמרא בהדיא בתירוץ רב אשי ופריך פשיטא מהו דתימא מיתקיל לישנא הוא דהיה לו לומר שאוכל לך ונתקל בלשונו לומר שאי קא משמע לן כיון שהוציא בשפתיו שאי אוכל לא מהימנינן ליה במה שאמר שהיה מגמגם כן כתב הרא\"ש פרק שני דנדרים:",
          "en": "",
          "ref": "Turei Zahav on Shulchan Arukh, Yoreh De'ah 237:5"
        },
        "6": {
          "he": "לשבועה לא אוכל לך. פי' כמו לא שבועה מה שלא אוכל הא מה שאוכל הוה שבועה ואע\"ג דבסי' ר\"ז קיי\"ל לענין נדרים דלא אמרינן מכלל לאו אתה שומע הן שבועות שאני כ\"כ רש\"י פרק שני דנדרים:",
          "en": "",
          "ref": "Turei Zahav on Shulchan Arukh, Yoreh De'ah 237:6"
        },
        "7": {
          "he": "בין הפציר כו'. פי' אפי' אם השיב תחלה לא אוכל והפציר בו ואמר השבועה שאוכל לך אפי' הכי שאוכל משמע:",
          "en": "",
          "ref": "Turei Zahav on Shulchan Arukh, Yoreh De'ah 237:7"
        }
      }
    },
    "pt": {
      "id": "pt",
      "name": "Pischei Teshuva",
      "hebrew": "פתחי תשובה",
      "seifim": {
        "1": {
          "he": "בשמים ובארץ. עיין בספר חכמת אדם כלל ע\"ט שכתב דזה מיירי שלא אמר הריני נשבע אלא אמר בשמים כו' אבל אם אמר הריני נשבע בשמים למה יגרע לשון שבועה בזה כיון דכוונתו למי שבראם ע\"ש:",
          "en": "",
          "ref": "Pitchei Teshuva on Shulchan Arukh, Yoreh De'ah 237:1"
        },
        "2": {
          "he": "כתב אשורית. עיין בתשובת חות יאיר סימן ק\"ו שכתב דכ\"ז מיירי בכתבו ישראל ובכוונה כו' אבל במנסה הקולמוס וכתב א\"ב אשורית וכן ספרי אקלודוס ואבן סיני של רפואות וכה\"ג בכתב אשורית בדפוס שאין בהם קדושת חומר ולא פועל במחשבתו ולא תכלית לנפש אף כי יש למנוע מלנהג בהם בזיון מ\"מ אין בהם קדושת ספרים להצילם מפני הדליקה בשבת והנשבע בהם אינו שבועה:",
          "en": "",
          "ref": "Pitchei Teshuva on Shulchan Arukh, Yoreh De'ah 237:2"
        }
      }
    },
    "bh": {
      "id": "bh",
      "name": "Ba'er Hetev",
      "hebrew": "באר היטב",
      "seifim": {
        "1": {
          "he": "שבועה.  ליש פוסקים איסורא איכא וליש פוסקים מלקות נמי איכא דלא גרע מידות שבועה וכתוב בתשובת מהר\"מ דאם הזכיר השם בלשון לע\"ז כגון דיא\"ו או גא\"ט אפי' לא הזכיר בתחלת דבריו לשם שבועה מועיל מטעם יד עכ\"ל ש\"ך:",
          "en": "",
          "ref": "Ba'er Hetev on Shulchan Arukh, Yoreh De'ah 237:1"
        },
        "2": {
          "he": "שיתכוין.  כ' הש\"ך משמע אף על פי שלא הזכיר שבועה קודם לכן ותמהני על מ\"ש הר\"ף ודוקא שהזכיר שבועה קודם שאמר הן הן וכו' דא\"כ אפי' אמר פעם א' לאו או הן הוי שבועה דלא גרע מידות ואפשר דמיירי שהזכיר מקודם לזה שבועה ואח\"כ הפסיק בינתים בענין דלא הוי יד:",
          "en": "",
          "ref": "Ba'er Hetev on Shulchan Arukh, Yoreh De'ah 237:2"
        },
        "3": {
          "he": "בשלחן.  ע\"ל סי' ר\"ד ס\"ב מה שיש לתמוה על הרמ\"א בכאן:",
          "en": "",
          "ref": "Ba'er Hetev on Shulchan Arukh, Yoreh De'ah 237:3"
        },
        "4": {
          "he": "שכתוב.  וכתוב בתשו' מהר\"מ מינץ דאם פתחן ונשבע בהן הוי כאומר במה שכתוב בהן ואע\"ג דמיירי שם בעשרת הדברות נראה דה\"ה לכל ספרי הקדש דחד טעמא אית להו. ש\"ך:",
          "en": "",
          "ref": "Ba'er Hetev on Shulchan Arukh, Yoreh De'ah 237:4"
        },
        "5": {
          "he": "הדברות.  כ' הש\"ך משמע דאם רק אמר אני נשבע בי' הדברות אע\"פ שאינו אוחזן בידו הוי שבועה וצריך התרה:",
          "en": "",
          "ref": "Ba'er Hetev on Shulchan Arukh, Yoreh De'ah 237:5"
        },
        "6": {
          "he": "שיכוין.  כלומר שכונתו לישבע בימין ושמאל של הקב\"ה ואז הוי שבועה אע\"פ שלא הזכיר לא שם ולא כינוי ודלא כדעת הב\"ח. ש\"ך:",
          "en": "",
          "ref": "Ba'er Hetev on Shulchan Arukh, Yoreh De'ah 237:6"
        },
        "7": {
          "he": "לשבועה.  כמו לא שבועה מה שלא אוכל הא מה שאוכל הוה שבועה ואע\"ג דקי\"ל לענין נדרים דלא אמרינן מכלל לאו כו' שאני שבועות כ\"כ רש\"י:",
          "en": "",
          "ref": "Ba'er Hetev on Shulchan Arukh, Yoreh De'ah 237:7"
        }
      }
    }
  },
  "enriched": {}
}