{
  "chelek": "CM",
  "siman": 274,
  "chelekTitle": "Choshen Mishpat",
  "seifCount": 1,
  "fetchedAt": "2026-07-08T00:09:16.293Z",
  "sa": [
    {
      "seif": 1,
      "he": "עכו\"ם שמכר שדה לישראל וקבל הדמים ולא כתב לו השטר הרי הוא כהפקר וכל הקודם בהם זכה ונתבאר בסימן קצ\"ד: הגה עשרה תנאים התנה יהושע בארץ וכולן נוהגות אף בחוץ לארץ וכתבן הרמב\"ם פ\"ה דהלכות נזקי ממון והטור סי' רע\"ד א' ולא ידעתי למה השמיטן המחבר הזה ואולי משום שאינן שכיחין שרובם אינן רק במקום שיש לישראל שדות וכרמים וזה אינו שכיח בגלות והרוצה לעמוד על דיניהן יעיין בפנים מי שהיה לו נחיל של דבורים ויצאו וישבו על אילן של חבירו י\"א דיכול לקוץ ענף כדי להציל נחילו ונותן דמי ענף לבעל האילן (טור בשם אביו הרא\"ש) ויש חולקין (שם בשם הרי\"ף והרמ\"ה):",
      "en": "",
      "ref": "Shulchan Arukh, Choshen Mishpat 274:1"
    }
  ],
  "commentaries": {
    "bg": {
      "id": "bg",
      "name": "Be'er HaGolah",
      "hebrew": "באר הגולה",
      "seifim": {
        "1": {
          "he": "א) וכולן מבוארים בגירא בפ\"ז דב\"ק דף פ\"א ע\"א:",
          "en": "",
          "ref": "Be'er HaGolah on Shulchan Arukh, Choshen Mishpat 274:1"
        },
        "2": {
          "he": "ב) בפסקיו בפ' הגוזל בתרא על מ\"ש הרי\"ף שאין הלכה כר' ישמעאל בזה שם במשנה דף קי\"ד ע\"א וכן אידך דרבי ישמעאל שם ע\"ב בברייתא תנאי ב\"ד הוא שיהא שופך יינו ומציל דובשנו של חבירו ונוטל דמי יינו ושיהא מפרק את עציו וטוען פשתנו של חבירו שמת חמורו ונוטל דמי עצו מתוך פשתנו של חבירו והביא ראיה לדבריו ודחה הרא\"ש שם ראיותיו וכתב דאפשר דהלכה נינהו ודין הדבש הביאו רמ\"א לעיל בסי' רע\"ד ס\"ד וע\"ש:",
          "en": "",
          "ref": "Be'er HaGolah on Shulchan Arukh, Choshen Mishpat 274:2"
        },
        "3": {
          "he": "ג) וכ\"פ הרמב\"ם בפ\"ב מה' גזילה די\"ד:",
          "en": "",
          "ref": "Be'er HaGolah on Shulchan Arukh, Choshen Mishpat 274:3"
        }
      }
    },
    "shach": {
      "id": "shach",
      "name": "Shach",
      "hebrew": "שך",
      "seifim": {
        "1": {
          "he": "וי\"ח  וכ\"פ מהרש\"ל פ\"י סי' כ\"ט ועיין עוד שם:",
          "en": "",
          "ref": "Siftei Kohen on Shulchan Arukh, Choshen Mishpat 274:1"
        }
      }
    },
    "bh": {
      "id": "bh",
      "name": "Ba'er Hetev",
      "hebrew": "באר היטב",
      "seifim": {
        "1": {
          "he": "זכה.  מיהו צריך לחזור וליתן כל הדמים לישראל כפי מה שנתן לעובד כוכבים ואם יש משפט ידוע בין העובדי כוכבים שלא קנהו אלא מי שנותן דמים הולכין אחר המשפט וכמבואר בסי' קצ\"ד ס\"ב ע\"ש כמה פרטי דינים מזה. סמ\"ע. (ראובן הניח לו עובד כוכבים אחד בחנותו איזה אמות סחור' ופגע העובד כוכבים בשמעון שהלך לקנות סחור' זו ממקום אחר וא\"ל לך וקח משלי שעומדת בחנות ראובן והלך שמעון ולקח ממנה ושכח העובד כוכבים הסחור' שקנ' שמעון וטען ראובן שהוא זכה בה כי העו\"ג הניחה בחנותו ושמעון טוען שבפקדון בא ליד ראובן וכל היכא דאיתא ברשותא דמריה אית' וברשות העובד כוכבים לקחה ולכן הוא זכה בה הדין עם שמעון. ועיין בתשובת מהרד\"ך בית י\"ט וגם מהר\"ר יעקב עוזיאל הסכים עמו בדין זה. בני אהרן סי' ל\"ב. בתשובת מ\"ב פסק בשם רוב המחברים כר\"ל דעובד כוכבים קונ' מישראל או ישראל מעובד כוכבים דוקא במעות ולא במשיכה ורמ\"א בתשוב' סי' כ\"ז פסק כר\"י דדוקא משיכה קונה בעובד כוכבים לא במעות ועיין בי\"ד סי' קל\"ב וסי' קמ\"ו והרש\"ך סי' קט\"ז כתב דדוקא משיכ' קונ' בעובד כוכבים מישראל או בישראל ממנו ומה\"ט פסק באחד שקנ' סחור' מעובד כוכבים ונתן מעות ולא משך ובא אחר וקנ' ומשך קנה השני ובתשובת מהרי\"ל סי' ר\"ט כתב דמספקא לן אי הלכה כר\"י או כר\"ל לכן בעינן תרווייהו ועיין בתשובת מהר\"מ מלובלין סי' ל\"א ומסיק ול\"נ הואיל ור\"ת ור\"י והרא\"ש ס\"ל דדוקא משיכ' קונ' בעובד כוכבים וגם הב\"י בסי' קמ\"ו וכן הרמ\"א והרש\"ך ואליבייהו גם הטור סובר כן וגם הב\"ח בסי' קל\"ב כ\"כ הכי נקטינן כת\"י אב\"ד משטרים עכ\"ל חקי משפט אות ה' סכ\"ח וכ\"ט וע\"ש עוד באות מ' סעיף קנ\"ד):",
          "en": "",
          "ref": "Ba'er Hetev on Shulchan Arukh, Choshen Mishpat 274:1"
        },
        "2": {
          "he": "חולקין.  וכ\"פ מהרש\"ל פ\"י דב\"ק סי' כ\"ט ועמ\"ש עוד שם. ש\"ך:",
          "en": "",
          "ref": "Ba'er Hetev on Shulchan Arukh, Choshen Mishpat 274:2"
        }
      }
    }
  },
  "enriched": {}
}